<?xml version="1.0" encoding="utf-8"?>
<lfm status="ok">
<artist>
  <name>Blof</name>
  <mbid></mbid>
    <url>http://www.last.fm/music/+noredirect/Blof</url>
  <image size="small">http://userserve-ak.last.fm/serve/34/31690803.jpg</image>
  <image size="medium">http://userserve-ak.last.fm/serve/64/31690803.jpg</image>
  <image size="large">http://userserve-ak.last.fm/serve/126/31690803.jpg</image>
  <image size="extralarge">http://userserve-ak.last.fm/serve/252/31690803.jpg</image>
  <image size="mega">http://userserve-ak.last.fm/serve/_/31690803/Blof+umojaoopshi.jpg</image>
  <streamable>0</streamable>
  <stats>
    <listeners>20698</listeners>
    <playcount>551769</playcount>
      </stats>

  <similar>
	    <artist>
	  <name>Bløf</name>
	  <url>http://www.last.fm/music/Bl%C3%B8f</url>
	  <image size="small">http://userserve-ak.last.fm/serve/34/8406073.jpg</image>
	  <image size="medium">http://userserve-ak.last.fm/serve/64/8406073.jpg</image>
	  <image size="large">http://userserve-ak.last.fm/serve/126/8406073.jpg</image>
	  <image size="extralarge">http://userserve-ak.last.fm/serve/252/8406073.jpg</image>
	  <image size="mega">http://userserve-ak.last.fm/serve/500/8406073/Blf++persfoto.jpg</image>
	  
	        	</artist>
    <artist>
	  <name>Acda en de Munnik</name>
	  <url>http://www.last.fm/music/Acda+en+de+Munnik</url>
	  <image size="small">http://userserve-ak.last.fm/serve/34/2291466.jpg</image>
	  <image size="medium">http://userserve-ak.last.fm/serve/64/2291466.jpg</image>
	  <image size="large">http://userserve-ak.last.fm/serve/126/2291466.jpg</image>
	  <image size="extralarge">http://userserve-ak.last.fm/serve/252/2291466.jpg</image>
	  <image size="mega">http://userserve-ak.last.fm/serve/500/2291466/Acda+en+de+Munnik+thomas_paul.jpg</image>
	  
	        	</artist>
    <artist>
	  <name>Marco Borsato</name>
	  <url>http://www.last.fm/music/Marco+Borsato</url>
	  <image size="small">http://userserve-ak.last.fm/serve/34/60880729.png</image>
	  <image size="medium">http://userserve-ak.last.fm/serve/64/60880729.png</image>
	  <image size="large">http://userserve-ak.last.fm/serve/126/60880729.png</image>
	  <image size="extralarge">http://userserve-ak.last.fm/serve/252/60880729.png</image>
	  <image size="mega">http://userserve-ak.last.fm/serve/_/60880729/Marco+Borsato.png</image>
	  
	        	</artist>
    <artist>
	  <name>Guus Meeuwis</name>
	  <url>http://www.last.fm/music/Guus+Meeuwis</url>
	  <image size="small">http://userserve-ak.last.fm/serve/34/186844.jpg</image>
	  <image size="medium">http://userserve-ak.last.fm/serve/64/186844.jpg</image>
	  <image size="large">http://userserve-ak.last.fm/serve/126/186844.jpg</image>
	  <image size="extralarge">http://userserve-ak.last.fm/serve/252/186844.jpg</image>
	  <image size="mega">http://userserve-ak.last.fm/serve/_/186844/Guus+Meeuwis.jpg</image>
	  
	        	</artist>
    <artist>
	  <name>Ilse DeLange</name>
	  <url>http://www.last.fm/music/Ilse+DeLange</url>
	  <image size="small">http://userserve-ak.last.fm/serve/34/51213817.png</image>
	  <image size="medium">http://userserve-ak.last.fm/serve/64/51213817.png</image>
	  <image size="large">http://userserve-ak.last.fm/serve/126/51213817.png</image>
	  <image size="extralarge">http://userserve-ak.last.fm/serve/252/51213817.png</image>
	  <image size="mega">http://userserve-ak.last.fm/serve/500/51213817/Ilse+DeLange+++Next+To+Me.png</image>
	  
	        	</artist>
  </similar>
    <tags>
        <tag>
	  <name>dutch</name>
	  <url>http://www.last.fm/tag/dutch</url>
	</tag>
        <tag>
	  <name>nederpop</name>
	  <url>http://www.last.fm/tag/nederpop</url>
	</tag>
        <tag>
	  <name>rock</name>
	  <url>http://www.last.fm/tag/rock</url>
	</tag>
        <tag>
	  <name>pop</name>
	  <url>http://www.last.fm/tag/pop</url>
	</tag>
        <tag>
	  <name>netherlands</name>
	  <url>http://www.last.fm/tag/netherlands</url>
	</tag>
      </tags>
      <bio>
    <published>Sun, 6 Feb 2011 20:09:39 +0000</published>
    <summary><![CDATA[BLØF (uitspraak: 'bluf') is een Nederlandse en Nederlandstalige popgroep uit Zeeland.  BLØF werd opgericht in 1992. Het eerste album, Naakt onder de hemel, werd in eigen beheer uitgebracht. In 1998 werd BLØF bekend bij het grote publiek met de single Liefs uit Londen waarna de populariteit van de band sterk steeg. De single kwam van het tweede album &quot;Helder&quot;. Na het succes van Liefs uit Londen worden live-versies van Aan de Kust en Wat zou je doen van het debuutalbum ook hits. Het derde album Boven brengt de hit Harder dan ik hebben kan.]]></summary>
    <content><![CDATA[BLØF (uitspraak: 'bluf') is een Nederlandse en Nederlandstalige popgroep uit Zeeland.  BLØF werd opgericht in 1992. Het eerste album, Naakt onder de hemel, werd in eigen beheer uitgebracht. In 1998 werd BLØF bekend bij het grote publiek met de single Liefs uit Londen waarna de populariteit van de band sterk steeg. De single kwam van het tweede album &quot;Helder&quot;. Na het succes van Liefs uit Londen worden live-versies van Aan de Kust en Wat zou je doen van het debuutalbum ook hits. Het derde album Boven brengt de hit Harder dan ik hebben kan. Niets dan dit en Zaterdag worden ook uitgebracht op single, maar worden minder grote hits. &quot;Zaterdag&quot; is wel elke zaterdagmorgen te horen als opener van het Radio 2-programma &quot;Cappuccino&quot;. Het vierde album Watermakers wordt voorafgegaan door de hit Dansen aan zee. Ook Hier en Ze is er niet worden hits.
    
User-contributed text is available under the Creative Commons By-SA License and may also be available under the GNU FDL.]]></content>
  </bio>
  </artist></lfm>
